SPIKES_TO_US_IN/__init__.py
SPIKES_TO_US_IN/model.py
SPIKES_TO_US_IN/model_fold.py
SPIKES_TO_US_IN/model_point.py
SPIKES_TO_US_IN/pf_pose.py
SPIKES_TO_US_IN/point_util.py
SPIKES_TO_US_IN/util_code.py
SPIKES_TO_US_IN-0.0.0.8.dist-info/LICENSE
SPIKES_TO_US_IN-0.0.0.8.dist-info/METADATA
SPIKES_TO_US_IN-0.0.0.8.dist-info/WHEEL
SPIKES_TO_US_IN-0.0.0.8.dist-info/top_level.txt
SPIKES_TO_US_IN-0.0.0.8.dist-info/RECORD
